pyrept/__init__.py
pyrept/html_report.py
pyrept/render.py
pyrept/templates/report.html
pyrept-1.0.2.dist-info/licenses/LICENSE
tests/__init__.py
tests/test_nose_plugin.py
tests/test_template_render.py
pyrept-1.0.2.dist-info/METADATA
pyrept-1.0.2.dist-info/WHEEL
pyrept-1.0.2.dist-info/top_level.txt
pyrept-1.0.2.dist-info/RECORD
