Metadata-Version: 2.4
Name: pyrept
Version: 1.0.2
Summary: This library generates both HTML and JSON reports for your Nose unit tests, providing a clear and structured overview of test results.
Home-page: https://github.com/pankajnayak1994/pyrept
Download-URL: https://github.com/pankajnayak1994/pyrept
Author: Pankaj Kumar Nayak
Author-email: nayakpankaj2015@gmail.com
License: MIT
Keywords: nose2,testing,reporting,pytest
Classifier: Development Status :: 3 - Alpha
Classifier: Intended Audience :: Developers
Classifier: Topic :: Software Development :: Testing
Classifier: License :: OSI Approved :: MIT License
Classifier: Programming Language :: Python :: 3.8
Classifier: Programming Language :: Python :: 3.9
Classifier: Programming Language :: Python :: 3.10
Classifier: Programming Language :: Python :: 3.11
Classifier: Programming Language :: Python :: 3.12
License-File: LICENSE
Requires-Dist: jinja2
Requires-Dist: nose2
Dynamic: author
Dynamic: author-email
Dynamic: classifier
Dynamic: description
Dynamic: description-content-type
Dynamic: download-url
Dynamic: home-page
Dynamic: keywords
Dynamic: license
Dynamic: license-file
Dynamic: requires-dist
Dynamic: summary
